Workbook

Sheet README
A1: KEEP — Scenario CAGR Matrix, 2026Q2 AUGMENTED (canonical, 73 rows)
A4: CANONICAL single-file build off the ratified SOURCE_UPDATE bundle. Supersedes and replaces: the interim 46-row
A5: AUGMENTED xlsx, KEEP_Scenario_CAGR_Matrix_2026Q2_AUGMENTED.pdf (394KB stale render), and the 3 interim CSVs
A6: (Scenario_CAGR_Matrix_FULL_2026Q2.csv, New_Tickers_CAGR_and_Betas_2026Q2.csv, New_Tickers_Betas_Deltas_2026Q2.csv).
A8: COVERAGE: 73 ticker rows x 20 scenarios. Provenance in Source column:
A9: house_2026Q1 (34) - original house rows. [unshaded]
A10: fitted_2026Q2 (12) - first augmentation pass. [orange]
A11: fitted_2026Q2_source_update - SOURCE_UPDATE additions. [blue]
A12: New names vs interim: JQUA, SMH, AVUS, HACK, ITA, PPA, MSCI, NDAQ, GD, LMT, NOC, RTX, URNM, XLV, CEG, EUAD,
A13: IBKR, GLD, plus market benchmarks (VOO/VTI/VT/VTSAX/IXUS/IEF) and proxy rows.
A15: CONSTRUCTION (per cell): CAGR%[t,s] = RF%[s] + SUMPRODUCT(beta[t,:],premia%[s,:]) + 12*alpha_m_shrunk%[t] + delta%[t,s]
A16: beta,alpha = FF5+Mom OLS on monthly excess returns, shrunk by w=n/(n+60). Single stocks matched-120mo; ETFs full
... A32: UNITS: CAGR, premia, deltas, alpha_m_shrunk in PERCENT; betas dimensionless. Generated 2026-06-28.

Sheet CAGR_Matrix_FULL
A1: Ticker | B1: Base Case – Managed Re-industrialization | C1: Reflation / Industrial Up-Cycle | D1: Stagflation / Fiscal Dominance | E1: Debt Overhang – Financial Repression | F1: Credit Stress – Shadow/Private Credit Accident | G1: AI Breakout – Productivity Boom / Concentration | H1: AI Breakout – Energy/Infrastructure Bottleneck | I1: Geopolitical Fragmentation – Trade/Tech Bifurcation | J1: Geopolitical Fragmentation – Cyber Systemic Event | K1: Cronyism / Policy Distortion | L1: China Hard Landing | M1: Taiwan Hostilities / Kinetic Shock | N1: Credit Accident (U.S. Regional) | O1: Space Race / Tech-Industrial Rivalry | P1: Pandemic / Bio Disruption | Q1: Climate Transition Stress – Policy/Stranding Shock | R1: Climate Stress – Physical/Insurance Retreat | S1: Energy Shock / Supply Constraint | T1: Political Polarization / Governance Shock | U1: Liquidity: JGB + US Fiscal Dominance | V1: Source
A2: AIRR | B2: 12.61 | C2: 15.08 | D2: 8.79 | E2: 8.56 | F2: -0.42 | G2: 10.95 | H2: 10.23 | I2: 6.85 | J2: 0.42 | K2: 8.29 | L2: 1.71 | M2: -1.41 | N2: 0.61 | O2: 13.24 | P2: 4.25 | Q2: 10.24 | R2: 6.48 | S2: 3.93 | T2: 6.23 | U2: 6.69 | V2: house_2026Q1
A3: AVDE | B3: 4.49 | C3: 6.1 | D3: 4.01 | E3: 3.96 | F3: 0.08 | G3: 4.36 | H3: 4.36 | I3: 2.59 | J3: -0.73 | K3: 3.94 | L3: -0.21 | M3: -0.7 | N3: 0.89 | O3: 4.29 | P3: 2.13 | Q3: 3.78 | R3: 2.73 | S3: 3.12 | T3: 2.97 | U3: 3.09 | V3: house_2026Q1
A4: AVUV | B4: 7.92 | C4: 11.13 | D4: 6.9 | E4: 6.18 | F4: -2.62 | G4: 6.94 | H4: 7.09 | I4: 4.94 | J4: -0.16 | K4: 5.81 | L4: 2.25 | M4: -1.46 | N4: -1.12 | O4: 7.86 | P4: 1.58 | Q4: 6.36 | R4: 4.82 | S4: 4 | T4: 4.26 | U4: 5.21 | V4: house_2026Q1
A5: BOTZ | B5: 4.11 | C5: 5.3 | D5: 0.96 | E5: 1.68 | F5: -4.35 | G5: 8.81 | H5: 5.05 | I5: -0.26 | J5: -6.18 | K5: 2.89 | L5: -2.75 | M5: -11.47 | N5: -4.81 | O5: 5.83 | P5: 2.21 | Q5: 3.17 | R5: 1.19 | S5: -2.72 | T5: 0.76 | U5: -0.05 | V5: house_2026Q1
A6: CIBR | B6: 9.05 | C6: 10.18 | D6: 6.55 | E6: 7.26 | F6: 4.39 | G6: 12.75 | H6: 9.14 | I6: 7.51 | J6: 5.23 | K6: 9.08 | L6: 5.28 | M6: 1.52 | N6: 3.97 | O6: 9.35 | P6: 8.16 | Q6: 8.31 | R6: 6.46 | S6: 4.77 | T6: 8.28 | U6: 7.38 | V6: house_2026Q1
A7: COWZ | B7: 7.63 | C7: 9.26 | D7: 7.46 | E7: 7.76 | F7: 3.81 | G7: 6.06 | H7: 7.02 | I7: 5.78 | J7: 1.31 | K7: 6.71 | L7: 3.5 | M7: 0.06 | N7: 3.21 | O7: 7.33 | P7: 4.43 | Q7: 6.39 | R7: 5.55 | S7: 4.78 | T7: 4.89 | U7: 7.1 | V7: house_2026Q1
A8: DFAS | B8: 6.03 | C8: 8.54 | D8: 3.89 | E8: 4.64 | F8: -2.66 | G8: 5.76 | H8: 5.66 | I8: 2.32 | J8: -1.84 | K8: 4.6 | L8: -0.91 | M8: -1.59 | N8: -1.39 | O8: 6.05 | P8: 0.78 | Q8: 4.92 | R8: 2.67 | S8: 2.96 | T8: 3.42 | U8: 2.68 | V8: house_2026Q1
A9: GRID | B9: 7.76 | C9: 9.36 | D9: 5.14 | E9: 4.86 | F9: -0.51 | G9: 8.54 | H9: 9.32 | I9: 3.58 | J9: -3.35 | K9: 4.9 | L9: 0.9 | M9: -4.14 | N9: -0.65 | O9: 7.79 | P9: 3.09 | Q9: 8.4 | R9: 4.6 | S9: 0.59 | T9: 2.89 | U9: 3.38 | V9: house_2026Q1
A10: IHI | B10: 8.97 | C10: 9.7 | D10: 7.64 | E10: 7.58 | F10: 3.51 | G10: 10.28 | H10: 8.8 | I10: 6.56 | J10: 1.19 | K10: 7.74 | L10: 4.31 | M10: -0.63 | N10: 2.9 | O10: 9.01 | P10: 6.67 | Q10: 8.02 | R10: 6.54 | S10: 4.55 | T10: 6.05 | U10: 6.44 | V10: house_2026Q1
A11: KOMP | B11: 8.26 | C11: 9.41 | D11: 5.04 | E11: 5.4 | F11: -0.43 | G11: 10.46 | H11: 8.29 | I11: 3.67 | J11: -1.7 | K11: 6.03 | L11: 1.33 | M11: -6.49 | N11: -0.49 | O11: 9.4 | P11: 5.38 | Q11: 6.61 | R11: 4.77 | S11: 0.94 | T11: 4.44 | U11: 3.7 | V11: house_2026Q1
A12: MOAT | B12: 7.7 | C12: 8.47 | D12: 7.89 | E12: 7.2 | F12: 4.42 | G12: 8.1 | H12: 7.46 | I12: 5.94 | J12: 1.32 | K12: 6.76 | L12: 3.82 | M12: -0.06 | N12: 3.02 | O12: 7.54 | P12: 4.85 | Q12: 6.8 | R12: 5.75 | S12: 4.69 | T12: 5.2 | U12: 6.07 | V12: house_2026Q1
A13: NLR | B13: 3.97 | C13: 4.69 | D13: 3.81 | E13: 2.84 | F13: -1.07 | G13: 4.44 | H13: 4.3 | I13: 2.53 | J13: -3.43 | K13: 2.96 | L13: -0.2 | M13: -3.93 | N13: -1.58 | O13: 3.9 | P13: 0.98 | Q13: 3.55 | R13: 2.35 | S13: 2.01 | T13: 0.81 | U13: 2.54 | V13: house_2026Q1
... A74: ZTS_proxy | B74: 7.2028 | C74: 7.7363 | D74: 7.2941 | E74: 6.7309 | F74: 3.7941 | G74: 8.2778 | H74: 7.1846 | I74: 5.7027 | J74: 1.4288 | K74: 6.3547 | L74: 3.6355 | M74: 0.039 | N74: 2.9282 | O74: 7.1124 | P74: 5.1636 | Q74: 6.3653 | R74: 5.6761 | S74: 4.3366 | T74: 5.0184 | U74: 5.8333 | V74: proxy_2026Q2_source_update

Sheet Betas_Shrunk_FULL
A1: Ticker | B1: n | C1: r2 | D1: shrink_w | E1: alpha_m_shrunk | F1: Mkt-RF | G1: SMB | H1: HML | I1: RMW | J1: CMA | K1: Mom | L1: Source
A2: AIRR | B2: 135 | C2: 0.8596 | D2: 0.6923 | E2: 0.1981 | F2: 0.7608 | G2: 0.6678 | H2: 0.1648 | I2: 0.1951 | J2: -0.1518 | K2: 0.0379 | L2: house_2026Q1
A3: AVDE | B3: 69 | C3: 0.8211 | D3: 0.5349 | E3: -0.0997 | F3: 0.4325 | G3: -0.0322 | H3: 0.1083 | I3: 0.0359 | J3: 0.0882 | K3: -0.1154 | L3: house_2026Q1
A4: AVUV | B4: 69 | C4: 0.9785 | D4: 0.5349 | E4: 0.0254 | F4: 0.5719 | G4: 0.4758 | H4: 0.2924 | I4: 0.1419 | J4: -0.0439 | K4: -0.0025 | L4: house_2026Q1
A5: BOTZ | B5: 105 | C5: 0.7837 | D5: 0.6364 | E5: -0.2303 | F5: 0.7864 | G5: 0.0063 | H5: -0.1236 | I5: -0.2516 | J5: -0.1173 | K5: -0.029 | L5: house_2026Q1
A6: CIBR | B6: 119 | C6: 0.7193 | D6: 0.6648 | E6: 0.2521 | F6: 0.645 | G6: 0.0543 | H6: -0.1864 | I6: -0.3293 | J6: -0.0758 | K6: 0.0695 | L6: house_2026Q1
A7: COWZ | B7: 102 | C7: 0.9087 | D7: 0.6296 | E7: 0.0266 | F7: 0.6091 | G7: 0.117 | H7: 0.1822 | I7: 0.1173 | J7: 0.1971 | K7: -0.085 | L7: house_2026Q1
A8: DFAS | B8: 48 | C8: 0.988 | D8: 0.4444 | E8: -0.0299 | F8: 0.4493 | G8: 0.3652 | H8: 0.1149 | I8: 0.0851 | J8: -0.0315 | K8: 0.0203 | L8: house_2026Q1
A9: GRID | B9: 187 | C9: 0.7826 | D9: 0.7571 | E9: -0.0962 | F9: 0.8121 | G9: 0.2337 | H9: -0.0013 | I9: 0.0491 | J9: -0.0581 | K9: -0.093 | L9: house_2026Q1
A10: IHI | B10: 229 | C10: 0.6919 | D10: 0.7924 | E10: 0.174 | F10: 0.73 | G10: 0.026 | H10: -0.1844 | I10: -0.2286 | J10: 0.1878 | K10: 0.0557 | L10: house_2026Q1
A11: KOMP | B11: 80 | C11: 0.948 | D11: 0.5714 | E11: 0.0983 | F11: 0.6443 | G11: 0.4307 | H11: -0.1119 | I11: -0.2837 | J11: 0.1131 | K11: 0.0076 | L11: house_2026Q1
A12: MOAT | B12: 158 | C12: 0.9044 | D12: 0.7248 | E12: 0.0888 | F12: 0.6814 | G12: -0.0444 | H12: 0.02 | I12: -0.0507 | J12: 0.0722 | K12: -0.2108 | L12: house_2026Q1
A13: NLR | B13: 214 | C13: 0.4267 | D13: 0.781 | E13: -0.2851 | F13: 0.6984 | G13: -0.0892 | H13: -0.0294 | I13: -0.0739 | J13: 0.0867 | K13: -0.0518 | L13: house_2026Q1
... A74: ZTS_proxy | B74: 227.2 | C74: 0.740907 | D74: 0.745822 | E74: 0.045864 | F74: 0.593498 | G74: -0.08606 | H74: -0.039404 | I74: 0.086848 | J74: 0.087515 | K74: 0.006362 | L74: proxy_2026Q2_source_update

Sheet Scenario_Deltas_FULL
A1: Ticker | B1: Base Case – Managed Re-industrialization | C1: Reflation / Industrial Up-Cycle | D1: Stagflation / Fiscal Dominance | E1: Debt Overhang – Financial Repression | F1: Credit Stress – Shadow/Private Credit Accident | G1: AI Breakout – Productivity Boom / Concentration | H1: AI Breakout – Energy/Infrastructure Bottleneck | I1: Geopolitical Fragmentation – Trade/Tech Bifurcation | J1: Geopolitical Fragmentation – Cyber Systemic Event | K1: Cronyism / Policy Distortion | L1: China Hard Landing | M1: Taiwan Hostilities / Kinetic Shock | N1: Credit Accident (U.S. Regional) | O1: Space Race / Tech-Industrial Rivalry | P1: Pandemic / Bio Disruption | Q1: Climate Transition Stress – Policy/Stranding Shock | R1: Climate Stress – Physical/Insurance Retreat | S1: Energy Shock / Supply Constraint | T1: Political Polarization / Governance Shock | U1: Liquidity: JGB + US Fiscal Dominance | V1: Source
A2: AIRR | B2: 1.5 | C2: 2.5 | D2: 0 | E2: 0 | F2: -2 | G2: 0 | H2: 0 | I2: 0 | J2: 0 | K2: 0 | L2: -2 | M2: 0 | N2: -1.5 | O2: 2 | P2: -2 | Q2: 1 | R2: -0.5 | S2: -1 | T2: 0 | U2: 0 | V2: house_2026Q1
A3: AVDE | B3: 0 | C3: 1 | D3: -1 | E3: 0 | F3: -1 | G3: 0 | H3: 0 | I3: -1 | J3: -1 | K3: 0 | L3: -2 | M3: 0 | N3: 0 | O3: 0 | P3: 0 | Q3: 0 | R3: -0.5 | S3: 0 | T3: 0 | U3: -1 | V3: house_2026Q1
A4: AVUV | B4: 0 | C4: 2 | D4: 0 | E4: 0 | F4: -3 | G4: 0 | H4: 0 | I4: 0 | J4: 0 | K4: 0 | L4: 0 | M4: 0 | N4: -2 | O4: 0 | P4: -2 | Q4: 0 | R4: 0 | S4: 0 | T4: 0 | U4: 0 | V4: house_2026Q1
A5: BOTZ | B5: 0 | C5: 0 | D5: -1.5 | E5: -0.5 | F5: -2 | G5: 3 | H5: 1 | I5: -1.5 | J5: -1.5 | K5: 0 | L5: -1.5 | M5: -5 | N5: -2 | O5: 1.5 | P5: 1 | Q5: 0 | R5: 0 | S5: -2 | T5: 0 | U5: -1 | V5: house_2026Q1
A6: CIBR | B6: 0 | C6: 0 | D6: -1 | E6: 0 | F6: 1 | G6: 2 | H6: 0 | I6: 1 | J6: 4 | K6: 1 | L6: 1 | M6: 2 | N6: 1 | O6: 0 | P6: 1.5 | Q6: 0 | R6: 0 | S6: 0 | T6: 2 | U6: 1 | V6: house_2026Q1
A7: COWZ | B7: 0 | C7: 1 | D7: 0 | E7: 1 | F7: 1.5 | G7: -1 | H7: 0 | I7: 0 | J7: 0 | K7: 0.5 | L7: 0 | M7: 0 | N7: 1 | O7: 0 | P7: 0 | Q7: 0 | R7: 0 | S7: 0 | T7: 0 | U7: 1 | V7: house_2026Q1
A8: DFAS | B8: 0 | C8: 1.5 | D8: -1.5 | E8: 0 | F8: -3 | G8: 0 | H8: 0 | I8: -1.5 | J8: -1.5 | K8: 0 | L8: -2.5 | M8: 0 | N8: -2 | O8: 0 | P8: -2 | Q8: 0 | R8: -1 | S8: 0 | T8: 0 | U8: -1.5 | V8: house_2026Q1
A9: GRID | B9: 1 | C9: 1.5 | D9: 0 | E9: 0 | F9: 0 | G9: 1 | H9: 3 | I9: 0 | J9: -1 | K9: 0 | L9: 0 | M9: 0 | N9: 0 | O9: 1 | P9: 0 | Q9: 3 | R9: 1 | S9: -1 | T9: 0 | U9: 0 | V9: house_2026Q1
A10: IHI | B10: 0 | C10: 0 | D10: 0 | E10: 0 | F10: 0 | G10: 0 | H10: 0 | I10: 0 | J10: 0 | K10: 0 | L10: 0 | M10: 0 | N10: 0 | O10: 0 | P10: 0 | Q10: 0 | R10: 0 | S10: 0 | T10: 0 | U10: 0 | V10: house_2026Q1
A11: KOMP | B11: 0.5 | C11: 0.5 | D11: -1 | E11: -0.5 | F11: -1.5 | G11: 2.5 | H11: 1 | I11: -1 | J11: -1 | K11: 0 | L11: -1 | M11: -4 | N11: -1.5 | O11: 1.5 | P11: 1 | Q11: 0 | R11: 0 | S11: -2 | T11: 0 | U11: -1 | V11: house_2026Q1
A12: MOAT | B12: 0 | C12: 0 | D12: 0.5 | E12: 0.5 | F12: 1.5 | G12: 0 | H12: 0 | I12: 0 | J12: 0 | K12: 0 | L12: 0 | M12: 0 | N12: 0.5 | O12: 0 | P12: 0 | Q12: 0 | R12: 0 | S12: 0 | T12: 0 | U12: 0 | V12: house_2026Q1
A13: NLR | B13: 0.5 | C13: 0.5 | D13: 1 | E13: 0.5 | F13: 0.5 | G13: 0 | H13: 1 | I13: 1 | J13: 0 | K13: 0.5 | L13: 0.5 | M13: 1 | N13: 0.5 | O13: 0.5 | P13: 0 | Q13: 1 | R13: 1 | S13: 2 | T13: 0 | U13: 1 | V13: house_2026Q1
... A74: ZTS_proxy | B74: 0 | C74: 0 | D74: 0.4 | E74: 0.4 | F74: 0.8 | G74: 0 | H74: 0 | I74: 0 | J74: 0 | K74: 0 | L74: 0 | M74: 0 | N74: 0.4 | O74: 0 | P74: 0 | Q74: 0 | R74: 0.2 | S74: 0 | T74: 0 | U74: 0 | V74: proxy_2026Q2_source_update

Sheet Scenario_Factor_Premia_pct
A1: Scenario | B1: RF | C1: Mkt-RF | D1: SMB | E1: HML | F1: RMW | G1: CMA | H1: Mom
A2: Base Case – Managed Re-industrialization | B2: 3 | C2: 6 | D2: 0.8 | E2: 2 | F2: 1.8 | G2: 0.8 | H2: 2
A3: Reflation / Industrial Up-Cycle | B3: 3.5 | C3: 6.5 | D3: 1.5 | E3: 2.5 | F3: 1 | G3: -0.5 | H3: 2
A4: Stagflation / Fiscal Dominance | B4: 4.5 | C4: 2.5 | D4: -1 | E4: 3 | F4: 2.5 | G4: 2 | H4: 0
A5: Debt Overhang – Financial Repression | B5: 3 | C5: 4 | D5: -0.5 | E5: 2 | F5: 2.5 | G5: 2.5 | H5: 1
A6: Credit Stress – Shadow/Private Credit Accident | B6: 2.5 | C6: -1.5 | D6: -3 | E6: -1.5 | F6: 3 | G6: 3 | H6: -1
A7: AI Breakout – Productivity Boom / Concentration | B7: 3 | C7: 7.5 | D7: -1 | E7: -2 | F7: 2.5 | G7: -1.5 | H7: 4
A8: AI Breakout – Energy/Infrastructure Bottleneck | B8: 3.5 | C8: 5 | D8: 0 | E8: 0.5 | F8: 2 | G8: 0 | H8: 2
A9: Geopolitical Fragmentation – Trade/Tech Bifurcation | B9: 3.5 | C9: 2 | D9: -1.5 | E9: 1.5 | F9: 2.5 | G9: 2 | H9: 0.5
A10: Geopolitical Fragmentation – Cyber Systemic Event | B10: 2.5 | C10: -4 | D10: -2.5 | E10: 0.5 | F10: 3.5 | G10: 3 | H10: -1.5
A11: Cronyism / Policy Distortion | B11: 3.5 | C11: 3.5 | D11: -1 | E11: 1 | F11: 1.5 | G11: 0.5 | H11: 1
A12: China Hard Landing | B12: 2.5 | C12: 0 | D12: -2 | E12: 0.5 | F12: 2.5 | G12: 2.5 | H12: -0.5
A13: Taiwan Hostilities / Kinetic Shock | B13: 2 | C13: -5.5 | D13: -3 | E13: 1.5 | F13: 3.5 | G13: 3 | H13: -2
... A21: Liquidity: JGB + US Fiscal Dominance | B21: 4.5 | C21: 0.5 | D21: -1.5 | E21: 2 | F21: 2.5 | G21: 2.5 | H21: 0

Sheet Scenarios
A1: Scenario | B1: Weight_% | C1: Weight_Normalized | D1: Severity_1to5 | E1: Canonical_Parent | F1: Notes_Merged | G1: Weight_Normalized_%
A2: Base Case – Managed Re-industrialization | B2: 17 | C2: 0.16666667 | D2: 2 | E2: Base Case – Managed Re-industrialization | F2: Core trajectory strengthened by fiscal & industrial policy; capex/reshoring. | G2: 16.667
A3: Reflation / Industrial Up-Cycle | B3: 10 | C3: 0.098039216 | D3: 2 | E3: Reflation / Industrial Up-Cycle | F3: Broad-based capex & reshoring tailwind; inflation contained. | G3: 9.804
A4: Stagflation / Fiscal Dominance | B4: 7 | C4: 0.068627451 | D4: 4 | E4: Stagflation / Fiscal Dominance | F4: Structural deficits + supply frictions persist; growth disappoints. | G4: 6.863
A5: Debt Overhang – Financial Repression | B5: 4 | C5: 0.039215686 | D5: 4 | E5: Debt Overhang / Credit Stress | F5: Inflate/grow away debt; negative real rates; stealth taxes/regulation. | G5: 3.922
A6: Credit Stress – Shadow/Private Credit Accident | B6: 3 | C6: 0.029411765 | D6: 4 | E6: Debt Overhang / Credit Stress | F6: Liquidity mismatch in private credit/shadow leverage triggers forced selling. | G6: 2.941
A7: AI Breakout – Productivity Boom / Concentration | B7: 5 | C7: 0.049019608 | D7: 3 | E7: AI Breakout / Tech Concentration | F7: Measured productivity inflects; equity leadership narrows; capex wave. | G7: 4.902
A8: AI Breakout – Energy/Infrastructure Bottleneck | B8: 3 | C8: 0.029411765 | D8: 3 | E8: AI Breakout / Tech Concentration | F8: Grid/transformers/power pricing constrain deployment; winners shift toward energy/infrastructure. | G8: 2.941
A9: Geopolitical Fragmentation – Trade/Tech Bifurcation | B9: 4 | C9: 0.039215686 | D9: 4 | E9: Geopolitical Fragmentation (Multipolar) | F9: Export controls, tariffs, friend-shoring; supply chains regionalize; cost of capital rises. | G9: 3.922
A10: Geopolitical Fragmentation – Cyber Systemic Event | B10: 4 | C10: 0.039215686 | D10: 5 | E10: Geopolitical Fragmentation (Multipolar) | F10: Payments/cloud/market plumbing disruption; risk premium spike; regulatory clampdown. | G10: 3.922
A11: Cronyism / Policy Distortion | B11: 6 | C11: 0.058823529 | D11: 3 | E11: Cronyism / Policy Distortion | F11: Policy captured; capital misallocated; productivity drag; episodic sector booms/busts. | G11: 5.882
A12: China Hard Landing | B12: 4 | C12: 0.039215686 | D12: 4 | E12: China Hard Landing | F12: Property/banking stress and weak demand transmit disinflation + commodity swings. | G12: 3.922
A13: Taiwan Hostilities / Kinetic Shock | B13: 4 | C13: 0.039215686 | D13: 5 | E13: Taiwan Hostilities / Kinetic Shock | F13: Semiconductor + shipping shock; rationing/controls; global recession risk. | G13: 3.922
... A21: Liquidity: JGB + US Fiscal Dominance | B21: 6 | C21: 0.058823529 | D21: 5 | E21: Liquidity: JGB + US Fiscal Dominance | F21: Compound liquidity shock from Japan yield repricing + US term premium/auction stress. | G21: 5.882

Sheet Added_Ticker_Audit
A1: Ticker | B1: Action | C1: Method | D1: PriceFit | E1: ProxyBase | F1: WeightedMeanCAGR_pct | G1: WorstCAGR_pct | H1: Note
A2: JQUA | B2: added_fit | C2: fitted_2026Q2_source_update | D2: n=91; r2=0.945; shrink=0.603 | F2: 5.5551926 | G2: -0.24635267 | H2: Avantis/quality sleeve; QUAL-style scenario deltas.
A3: SMH | B3: added_fit | C3: fitted_2026Q2_source_update | D3: n=300; r2=0.682; shrink=0.833 | F3: 8.2573424 | G3: -10.514191 | H3: Semiconductor sleeve; SOXX-style scenario deltas.
A4: AVUS | B4: added_fit | C4: fitted_2026Q2_source_update | D4: n=69; r2=0.995; shrink=0.535 | F4: 4.6377148 | G4: -1.1865529 | H4: Broad US Avantis core; factor-only zero discretionary deltas.
A5: HACK | B5: added_fit | C5: fitted_2026Q2_source_update | D5: n=127; r2=0.689; shrink=0.679 | F5: 6.1638343 | G5: -0.52452921 | H5: Cybersecurity; IHAK-style scenario deltas.
A6: ITA | B6: added_fit | C6: fitted_2026Q2_source_update | D6: n=229; r2=0.703; shrink=0.792 | F6: 8.7932396 | G6: 1.9137608 | H6: Aerospace/defense ETF; XAR/ROKT blended defense deltas.
A7: PPA | B7: added_fit | C7: fitted_2026Q2_source_update | D7: n=236; r2=0.742; shrink=0.797 | F7: 8.7778927 | G7: 1.8891039 | H7: Aerospace/defense ETF; XAR/ROKT blended defense deltas.
A8: IXUS | B8: added_fit | C8: fitted_2026Q2_source_update | D8: n=152; r2=0.730; shrink=0.717 | F8: 1.9483886 | G8: -3.0132924 | H8: Broad ex-US equity; AVDE-style developed-intl deltas.
A9: MSCI | B9: added_fit | C9: fitted_2026Q2_source_update | D9: n=120; r2=0.528; shrink=0.667 | F9: 12.975974 | G9: 4.6324776 | H9: Index/data tollbooth; 120m single-stock fit; scaled SPGI-style deltas.
A10: NDAQ | B10: added_fit | C10: fitted_2026Q2_source_update | D10: n=120; r2=0.464; shrink=0.667 | F10: 10.381482 | G10: 3.8860374 | H10: Exchange/data; 120m single-stock fit; ICE-style exchange deltas.
A11: NOC | B11: added_fit | C11: fitted_2026Q2_source_update | D11: n=120; r2=0.244; shrink=0.667 | F11: 9.0755516 | G11: 4.7246897 | H11: Prime defense contractor; 120m fit; defense deltas.
A12: LMT | B12: added_fit | C12: fitted_2026Q2_source_update | D12: n=120; r2=0.295; shrink=0.667 | F12: 7.4991793 | G12: 3.5800762 | H12: Prime defense contractor; 120m fit; defense deltas.
A13: GD | B13: added_fit | C13: fitted_2026Q2_source_update | D13: n=120; r2=0.388; shrink=0.667 | F13: 6.2306809 | G13: 1.8129533 | H13: Prime defense contractor; 120m fit; defense deltas.
... A18: XLV | B18: added_fit | C18: fitted_2026Q2_source_update | D18: n=318; r2=0.605; shrink=0.841 | F18: 6.0592849 | G18: 0.22922444 | H18: Healthcare sector benchmark; factor-only zero discretionary deltas.
A19: EUAD | B19: added_proxy | C19: proxy_2026Q2_source_update | D19: proxy blend | E19: 0.6*XAR;0.4*ROKT | F19: 8.2034902 | G19: 1.412 | H19: EUAD had too little usable local history in bundle; Europe aerospace/defense represented by XAR/ROKT blended defense proxy.
A20: VOO | B20: added_proxy | C20: proxy_2026Q2_source_update | D20: proxy blend | E20: 1*IVV | F20: 4.9871569 | G20: -1.21 | H20: VOO treated as IVV/S&P 500 benchmark equivalent; use actual VOO price later if desired.
A21: GLD | B21: added_proxy | C21: proxy_2026Q2_source_update | D21: proxy blend | E21: 1*GLDM | F21: 9.5616176 | G21: 7.89 | H21: GLD treated as GLDM scenario-equivalent; apply higher ER separately in portfolio engine.
A22: IEF/aggregate-bond proxy | B22: added_proxy | C22: proxy_2026Q2_source_update | D22: proxy blend | E22: 1*IEF | F22: 4.8342182 | G22: 3.8503737 | H22: Exact alias for weights_matrix_all_ports legacy label.
A23: VTI | B23: added_proxy | C23: proxy_2026Q2_source_update | D23: proxy blend | E23: 0.8*IVV;0.2*AVUS | F23: 4.9172684 | G23: -1.2053106 | H23: Broad US market proxy: 80% IVV + 20% AVUS.
A24: VTSAX | B24: added_proxy | C24: proxy_2026Q2_source_update | D24: proxy blend | E24: 1*VTI | F24: 4.9172684 | G24: -1.2053106 | H24: VTSAX treated as VTI total-US proxy.
A25: VT | B25: added_proxy | C25: proxy_2026Q2_source_update | D25: proxy blend | E25: 0.55*VTI;0.45*IXUS | F25: 3.5812725 | G25: -2.0189024 | H25: Global equity proxy: 55% US total market + 45% ex-US.
A26: PSCI | B26: added_proxy | C26: proxy_2026Q2_source_update | D26: proxy blend | E26: 0.5*AIRR;0.3*XAR;0.2*PAVE | F26: 8.2959804 | G26: 0.257 | H26: Small-cap industrial proxy: AIRR/XAR/PAVE blend; no local PSCI price in bundle.
A27: IBKR | B27: added_proxy | C27: proxy_2026Q2_source_update | D27: proxy blend | E27: 0.5*NDAQ;0.3*CBOE;0.2*ICE | F27: 9.7476624 | G27: 4.5290187 | H27: Brokerage/market-structure proxy; no local IBKR price in bundle, so use exchange/data blend.
A28: ZTS_proxy | B28: added_proxy | C28: proxy_2026Q2_source_update | D28: proxy blend | E28: 0.6*XLV;0.4*JQUA | F28: 5.857648 | G28: 0.038993599 | H28: ZTS rough animal-health quality/healthcare proxy; label kept explicit, not a true ticker row.

Sheet Coverage_Audit
A1: Portfolio | B1: Family | C1: TickerCount | D1: WeightTotal_pct | E1: CoveredWeight_Before | F1: MissingBefore | G1: CoveredWeight_After | H1: MissingAfter
A2: port_100pct_AVUS_proxy | B2: OPT_bundle | C2: 1 | D2: 100 | E2: 0 | F2: AVUS | G2: 1
A3: NOC_LMT_HardWorld_Test | B3: manual_recent | C3: 5 | D3: 100 | E3: 0.1 | F3: NOC;LMT;GD;RTX | G3: 1
A4: Versus_Market_Benchmarks | B4: manual_recent | C4: 7 | D4: 100 | E4: 0.25 | F4: VOO;VTI;VT;AVUS;VTSAX;IXUS | G4: 1
A5: IBKR_NDAQ_Exchange_Test | B5: manual_recent | C5: 5 | D5: 100 | E5: 0.3 | F5: IBKR;NDAQ | G5: 1
A6: port_AVUS50_AVUV50_proxy | B6: OPT_bundle | C6: 2 | D6: 100 | E6: 0.5 | F6: AVUS | G6: 1
A7: port_target_date_2070_VSVNX_proxy | B7: OPT_bundle | C7: 3 | D7: 100 | E7: 0.52 | F7: IEF/aggregate-bond proxy;IXUS | G7: 1
A8: port_median_investor_60IVV_20IXUS_20IEF_proxy | B8: OPT_bundle | C8: 3 | D8: 100 | E8: 0.6 | F8: IEF;IXUS | G8: 1
A9: Evergreen_20260612 | B9: manual_recent | C9: 21 | D9: 100 | E9: 0.8 | F9: PPA;JQUA;MSCI;ITA;EUAD;HACK | G9: 1
A10: OPT_TollboothOnly_41 | B10: pathce_candidates | C10: 13 | D10: 100 | E10: 0.82 | F10: JQUA;SMH | G10: 1
A11: PASS2_prudence_capped | B11: OPT_bundle | C11: 16 | D11: 100 | E11: 0.83 | F11: HACK;ITA;MSCI;PPA | G11: 1
A12: OPT_TollboothOnly_21 | B12: pathce_candidates | C12: 12 | D12: 100 | E12: 0.87 | F12: JQUA | G12: 1
A13: Hybrid_Productivity | B13: OPT_bundle | C13: 16 | D13: 100 | E13: 0.88 | F13: JQUA;SMH | G13: 1
... A48: OPT_TollboothOnly_47 | B48: pathce_candidates | C48: 12 | D48: 100 | E48: 0.99 | F48: JQUA | G48: 1
A49: 20260623_Modest_basket | B49: manual_recent | C49: 9 | D49: 100 | E49: 1 | G49: 1
A50: 20260623_current | B50: manual_recent | C50: 17 | D50: 100 | E50: 1 | G50: 1
A51: Md2_CTA | B51: manual_recent | C51: 12 | D51: 100 | E51: 1 | G51: 1
A52: Md2_ICE | B52: manual_recent | C52: 12 | D52: 100 | E52: 1 | G52: 1
A53: Md_11_fewer_holdings | B53: manual_recent | C53: 11 | D53: 100 | E53: 1 | G53: 1
A54: OPT_TollboothOnly_1 | B54: OPT_bundle | C54: 14 | D54: 100 | E54: 1 | G54: 1
A55: OPT_TollboothOnly_11 | B55: OPT_bundle | C55: 13 | D55: 100 | E55: 1 | G55: 1
A56: OPT_TollboothOnly_18 | B56: OPT_bundle | C56: 12 | D56: 100 | E56: 1 | G56: 1
A57: OPT_TollboothOnly_23 | B57: pathce_candidates | C57: 14 | D57: 100 | E57: 1 | G57: 1
A58: OPT_TollboothOnly_24 | B58: pathce_candidates | C58: 12 | D58: 100 | E58: 1 | G58: 1
A59: OPT_TollboothOnly_28 | B59: pathce_candidates | C59: 13 | D59: 100 | E59: 1 | G59: 1
A60: OPT_TollboothOnly_32 | B60: pathce_candidates | C60: 13 | D60: 100 | E60: 1 | G60: 1
... A72: port_100pct_SP500_IVV_proxy | B72: OPT_bundle | C72: 1 | D72: 100 | E72: 1 | G72: 1

Sheet Reconstruction_Check
A1: Check (ticker x scenario, provenance) | B1: RF | C1: p_Mkt-RF | D1: p_SMB | E1: p_HML | F1: p_RMW | G1: p_CMA | H1: p_Mom | I1: b_Mkt-RF | J1: b_SMB | K1: b_HML | L1: b_RMW | M1: b_CMA | N1: b_Mom | O1: alpha_m | P1: delta | Q1: recon | R1: stored | S1: diff
A2: QTUM x Stagflation / Fiscal Dom [fitted_2026Q2] | B2: =Scenario_Factor_Premia_pct!B4 -> 4.5 | C2: =Scenario_Factor_Premia_pct!C4 -> 2.5 | D2: =Scenario_Factor_Premia_pct!D4 -> -1 | E2: =Scenario_Factor_Premia_pct!E4 -> 3 | F2: =Scenario_Factor_Premia_pct!F4 -> 2.5 | G2: =Scenario_Factor_Premia_pct!G4 -> 2 | H2: =Scenario_Factor_Premia_pct!H4 -> 0 | I2: =Betas_Shrunk_FULL!F45 -> 0.6034 | J2: =Betas_Shrunk_FULL!G45 -> 0.1311 | K2: =Betas_Shrunk_FULL!H45 -> -0.1485 | L2: =Betas_Shrunk_FULL!I45 -> -0.0718 | M2: =Betas_Shrunk_FULL!J45 -> 0.0651 | N2: =Betas_Shrunk_FULL!K45 -> -0.0942 | O2: =Betas_Shrunk_FULL!E45 -> 0.4974 | P2: =Scenario_Deltas_FULL!D45 -> 0 | Q2: =B2+SUMPRODUCT(C2:H2,I2:N2)+12*O2+P2 -> 11.3514 | R2: =CAGR_Matrix_FULL!D45 -> 11.35 | S2: =Q2-R2 -> 0.0014
A3: CEG x Credit Stress – Shadow/P [fitted_2026Q2_source_update] | B3: =Scenario_Factor_Premia_pct!B6 -> 2.5 | C3: =Scenario_Factor_Premia_pct!C6 -> -1.5 | D3: =Scenario_Factor_Premia_pct!D6 -> -3 | E3: =Scenario_Factor_Premia_pct!E6 -> -1.5 | F3: =Scenario_Factor_Premia_pct!F6 -> 3 | G3: =Scenario_Factor_Premia_pct!G6 -> 3 | H3: =Scenario_Factor_Premia_pct!H6 -> -1 | I3: =Betas_Shrunk_FULL!F49 -> 0.562042 | J3: =Betas_Shrunk_FULL!G49 -> 0.135706 | K3: =Betas_Shrunk_FULL!H49 -> -0.337872 | L3: =Betas_Shrunk_FULL!I49 -> -0.256122 | M3: =Betas_Shrunk_FULL!J49 -> 0.084283 | N3: =Betas_Shrunk_FULL!K49 -> 0.607364 | O3: =Betas_Shrunk_FULL!E49 -> 1.684222 | P3: =Scenario_Deltas_FULL!F49 -> 0.25 | Q3: =B3+SUMPRODUCT(C3:H3,I3:N3)+12*O3+P3 -> 21.09441 | R3: =CAGR_Matrix_FULL!F49 -> 21.0944 | S3: =Q3-R3 -> 1e-05
A4: MOAT x Base Case – Managed Re-i [house_2026Q1] | B4: =Scenario_Factor_Premia_pct!B2 -> 3 | C4: =Scenario_Factor_Premia_pct!C2 -> 6 | D4: =Scenario_Factor_Premia_pct!D2 -> 0.8 | E4: =Scenario_Factor_Premia_pct!E2 -> 2 | F4: =Scenario_Factor_Premia_pct!F2 -> 1.8 | G4: =Scenario_Factor_Premia_pct!G2 -> 0.8 | H4: =Scenario_Factor_Premia_pct!H2 -> 2 | I4: =Betas_Shrunk_FULL!F12 -> 0.6814 | J4: =Betas_Shrunk_FULL!G12 -> -0.0444 | K4: =Betas_Shrunk_FULL!H12 -> 0.02 | L4: =Betas_Shrunk_FULL!I12 -> -0.0507 | M4: =Betas_Shrunk_FULL!J12 -> 0.0722 | N4: =Betas_Shrunk_FULL!K12 -> -0.2108 | O4: =Betas_Shrunk_FULL!E12 -> 0.0888 | P4: =Scenario_Deltas_FULL!B12 -> 0 | Q4: =B4+SUMPRODUCT(C4:H4,I4:N4)+12*O4+P4 -> 7.70338 | R4: =CAGR_Matrix_FULL!B12 -> 7.7 | S4: =Q4-R4 -> 0.00338
A5: IEF/aggregate-bond proxy x Base Case – Managed Re-i [proxy_2026Q2_source_update] | B5: =Scenario_Factor_Premia_pct!B2 -> 3 | C5: =Scenario_Factor_Premia_pct!C2 -> 6 | D5: =Scenario_Factor_Premia_pct!D2 -> 0.8 | E5: =Scenario_Factor_Premia_pct!E2 -> 2 | F5: =Scenario_Factor_Premia_pct!F2 -> 1.8 | G5: =Scenario_Factor_Premia_pct!G2 -> 0.8 | H5: =Scenario_Factor_Premia_pct!H2 -> 2 | I5: =Betas_Shrunk_FULL!F56 -> -0.020322 | J5: =Betas_Shrunk_FULL!G56 -> -0.030079 | K5: =Betas_Shrunk_FULL!H56 -> -0.096099 | L5: =Betas_Shrunk_FULL!I56 -> 0.096169 | M5: =Betas_Shrunk_FULL!J56 -> -0.011631 | N5: =Betas_Shrunk_FULL!K56 -> -0.010034 | O5: =Betas_Shrunk_FULL!E56 -> 0.140493 | P5: =Scenario_Deltas_FULL!B56 -> 0 | Q5: =B5+SUMPRODUCT(C5:H5,I5:N5)+12*O5+P5 -> 4.4914542 | R5: =CAGR_Matrix_FULL!B56 -> 4.4915 | S5: =Q5-R5 -> -4.58e-05
